pstar/__init__.py
pstar/pstar.py
pstar-1.0.0.dist-info/licenses/LICENSE
pstar-1.0.0.dist-info/METADATA
pstar-1.0.0.dist-info/WHEEL
pstar-1.0.0.dist-info/top_level.txt
pstar-1.0.0.dist-info/RECORD
