Metadata-Version: 2.4
Name: pstar
Version: 1.0.0
Summary: pstar: numpy for arbitrary data
Home-page: https://github.com/itfische/pstar
Download-URL: https://github.com/itfische/pstar/archive/1.0.0.tar.gz
Author: Ian Fischer
Author-email: itfische@gmail.com
License: Apache 2.0
License-File: LICENSE
Requires-Dist: qj
Dynamic: author
Dynamic: author-email
Dynamic: description
Dynamic: description-content-type
Dynamic: download-url
Dynamic: home-page
Dynamic: license
Dynamic: license-file
Dynamic: requires-dist
Dynamic: summary
